<pages>
<link>
<title>Child Sexual Abuse Law</title>
<url>
https://en.wikipedia.org/wiki/Child_sexual_abuse_laws_in_India
</url>
</link>

<link>
<title>Anti-Corruption Laws</title>
<url>https://en.wikipedia.org/wiki/Prevention_of_Corruption_Act,_1988</url>
</link>

<link>
<title>Anti-Hijacking Act</title>
<url>https://en.wikipedia.org/wiki/Aircraft_hijacking</url>
</link>

<link>
<title>Child Labour (Prohibition and Regulation) Act</title>
<url>https://en.wikipedia.org/wiki/Child_Labour_(Prohibition_and_Regulation)_Act</url>
</link>

<link>
<title>Dowry Prohibition Act  </title>
<url>https://en.wikipedia.org/wiki/Dowry_system_in_India</url>
</link>

<link>
<title>Drugs (Control) Act </title>
<url>https://en.wikipedia.org/wiki/Drugs_Control_Act,_1950</url>
</link>

<link>
<title>Child Marriage Restraint Act</title>
<url>https://en.wikipedia.org/wiki/Child_Marriage_Restraint_Act</url>
</link>

<link>
<title>Election Laws</title>
<url>https://en.wikipedia.org/wiki/Elections_in_India</url>
</link>

<link>
<title>Illegal Migrants (Determination by Tribunals) Act</title>
<url>https://en.wikipedia.org/wiki/Illegal_Migrants_(Determination_by_Tribunal)_Act,_1983</url>
</link>

<link>
<title>Indian Divorce Act</title>
<url>https://en.wikipedia.org/wiki/Divorce_law_by_country</url>
</link>

<link>
<title>Energy Conservation Act</title>
<url>https://en.wikipedia.org/wiki/Energy_conservation</url>
</link>

<link>
<title>Income-tax Act</title>
<url>https://en.wikipedia.org/wiki/The_Income-tax_Act,_1961</url>
</link>

<link>
    <title> Law Meaning,Features,Sources and Types </title>
    <url> http://www.yourarticlelibrary.com/essay/law-essay/law-meaning-features-sources-and-types-of-law/40363</url>
</link>

<link>
    <title> Types and Classification of laws </title>
    <url> http://www.djetlawyer.com/types-classifications-law/</url>
</link>

<link>
    <title> Molestation</title>
    <url>https://www.nrilegalservices.com/molestation-definition-relevant-laws/</url>
</link>

<link>
    <title> Sexual Harassment</title>
    <url>http://www.legalserviceindia.com/articles/rape_laws.htm</url>
</link>
<link>
    <title> Types of Laws</title>
    <url>http://www.civicsandcitizenship.edu.au/cce/pl_law_types,9538.html</url>
</link>
<link>
    <title> What is Law </title>
    <url> https://en.wikipedia.org/wiki/Law </url>
</link>
<link>
    <title>  4 Main Types of Laws</title>
    <url>http://uhrlawoffice.com/index.php?id=24</url>
</link>
<link>
<title>Indian Tolls Act</title>
<url>https://en.wikipedia.org/wiki/Toll_road</url>
</link>

<link>
<title>Land Acquisition Act</title>
<url>https://en.wikipedia.org/wiki/Land_acquisition_in_India</url>
</link>

<link>
<title>Insurance Regulatory and Development Authority Act</title>
<url>https://en.wikipedia.org/wiki/Insurance_Regulatory_and_Development_Authority</url>
</link>

<link>
<title>Life Insurance Corporation Act</title>
<url>https://en.wikipedia.org/wiki/Life_Insurance_Corporation</url>
</link>

<link>
<title>Metro Railways (Construction of Works) Act</title>
<url>https://en.wikipedia.org/wiki/Metro_Railways_Act,_1978</url>
</link>

<link>
<title>Industrial Employment (Standing Orders) Act</title>
<url>https://en.wikipedia.org/wiki/Employment_Act_of_1946</url>
</link>

<link>
<title>National Service Act</title>
<url>https://en.wikipedia.org/wiki/National_Service_Act</url>
</link>

<link>
<title>Navy Act</title>
<url>https://en.wikipedia.org/wiki/Naval_Act_of_1794</url>
</link>

<link>
<title>Mines and Minerals (Regulation and Development) Act</title>
<url>https://en.wikipedia.org/wiki/Mines_and_Minerals_(Development_and_Regulation)_Act,_1957</url>
</link>

<link>
<title>Passport (Entry into India) Act</title>
<url>https://en.wikipedia.org/wiki/Indian_passport</url>
</link>

<link>
<title>Patents Act  </title>
<url>https://en.wikipedia.org/wiki/Patent_Act</url>
</link>

<link>
<title>Pensions Act</title>
<url>https://en.wikipedia.org/wiki/Pensions_Act_1995</url>
</link>

<link>
<title>Police Forces (Restriction of Rights) Act</title>
<url>https://en.wikipedia.org/wiki/List_of_Acts_of_the_Parliament_of_India</url>
</link>

<link>
<title>Press Council Act</title>
<url>https://en.wikipedia.org/wiki/Press_Council_of_India</url>
</link>

<link>
<title>Powers-of-Attorney Act</title>
<url>https://en.wikipedia.org/wiki/Power_of_attorney</url>
</link>

<link>
<title>Prevention of Blackmarketing and Maintenance of Supplies of Essential Commodities Act</title>
<url>https://en.wikipedia.org/wiki/Essential_Commodities_Act</url>
</link>

<link>
<title>Prevention of Damage to Public Property Act </title>
<url>https://en.wikipedia.org/wiki/Property_damage</url>
</link>

<link>
<title>Prevention of Food Adulteration Act  </title>
<url>https://en.wikipedia.org/wiki/Adulterated_food></url>
</link>

<link>
<title>Prisoners Act</title>
<url>https://en.wikipedia.org/wiki/Prison_Act_1877</url>
</link>

<link>
<title>Protection of Civil Rights Act </title>
<url>https://en.wikipedia.org/wiki/Civil_Rights_Act_of_1964</url>
</link>

<link>
<title>Protection of Human Rights Act, 1993 </title>
<url>https://en.wikipedia.org/wiki/National_Human_Rights_Commission_of_India</url>
</link>

<link>
<title>Provident Funds Act </title>
<url>https://en.wikipedia.org/wiki/Employees%27_Provident_Fund_Organisation</url>
</link>

<link>
<title>Provisional Collection of Taxes Act </title>
<url>https://en.wikipedia.org/wiki/Taxation_in_India</url>
</link>

<link>
<title>Public Financial Institutions (Obligation as to Fidelity  and Secrecy) Act </title>
<url>https://en.wikipedia.org/wiki/List_of_Acts_of_the_Parliament_of_India</url>
</link>

<link>
<title>Railway Protection Force Act  </title>
<url>https://en.wikipedia.org/wiki/Railway_Protection_Force</url>
</link>

<link>
<title>Rent Recovery Act </title>
<url>https://en.wikipedia.org/wiki/Debt_collection</url>
</link>

<link>
<title>Public Records Act </title>
<url>https://en.wikipedia.org/wiki/Public_Records_Act_1958</url>
</link>

<link>
<title>Railways Employment of Members of the Armed Forces Act </title>
<url>https://en.wikipedia.org/wiki/Indian_Railway_Personnel_Service</url>
</link>

<link>
<title>Reserve Bank (Transfer of Public Ownership) Act  </title>
<url>https://en.wikipedia.org/wiki/Reserve_Bank_of_India</url>
</link>

<link>
<title>Smugglers and Foreign Exchange Manipulators (Forfeiture of  Property) Act</title>
<url>https://en.wikipedia.org/wiki/Investigation_Division_of_the_Central_Board_of_Direct_Taxes</url>
</link>

<link>
<title>Sales Tax Laws Validation Act </title>
<url>https://en.wikipedia.org/wiki/Goods_and_Services_Tax_(India)</url>
</link>

<link>
<title>State Financial Corporations Act</title>
<url>https://en.wikipedia.org/wiki/Category:State_financial_corporations_of_India</url>
</link>

<link>
<title>Union Territories (Laws) Act</title>
<url>https://en.wikipedia.org/wiki/Union_territory</url>
</link>

<link>
<title>Warehousing Corporations Act</title>
<url>https://en.wikipedia.org/wiki/Central_Warehousing_Corporation</url>
</link>

<link>
<title>Water (Prevention and Control of Pollution) Act  </title>
<url>https://en.wikipedia.org/wiki/Central_Pollution_Control_Board</url>
</link>

<link>
<title>Wealth-tax Act </title>
<url>https://en.wikipedia.org/wiki/Wealth_Tax_Act,_1957</url>
</link>

<link>
<title>Trading with the Enemy (Continuance of Emergency Provisions)  Act </title>
<url>https://en.wikipedia.org/wiki/Trading_with_the_Enemy_Act_of_1917</url>
</link>

<link>
<title>Wild Life (Protection) Act </title>
<url>https://en.wikipedia.org/wiki/Wildlife_Protection_Act,_1972</url>
</link>

<link>
<title>Tobacco Board Act </title>
<url>https://en.wikipedia.org/wiki/Cigarettes_and_Other_Tobacco_Products_Act</url>
</link>
</pages>